<?xml version="1.0" encoding="UTF-8" standalone="yes"?>
<items>


<item>
<title>A Agência 1ª Temporada - (2025)[COLOR yellow] +14 [/COLOR]</title>
<link>plugin://plugin.video.elementum/play?uri=magnet:?xt=urn:btih:98fff7605af1b6c365d31efa92d83f54facbbafc$nome=[COLOR yellow]Série - A Agência 1ª Temp. Ep.01 (2025)[/COLOR]</link>
<link>plugin://plugin.video.elementum/play?uri=magnet:?xt=urn:btih:e9d09307955c44dcf107e5dc6c1fa40661f2bf9d$nome=[COLOR yellow]Série - A Agência 1ª Temp. Ep.02 (2025)[/COLOR]</link>
<link>plugin://plugin.video.elementum/play?uri=magnet:?xt=urn:btih:b154031578aa4e7c58a77f34733cb97a7c018577$nome=[COLOR yellow]Série - A Agência 1ª Temp. Ep.03 (2025)[/COLOR]</link>
<link>plugin://plugin.video.elementum/play?uri=magnet:?xt=urn:btih:744d93406497e26a11c29a7af6ac7e58a203e913$nome=[COLOR yellow]Série - A Agência 1ª Temp. Ep.04 (2025)[/COLOR]</link>
<link>plugin://plugin.video.elementum/play?uri=magnet:?xt=urn:btih:23a4ab91fd359253660e7948be17dadffe8f155a$nome=[COLOR yellow]Série - A Agência 1ª Temp. Ep.05 (2025)[/COLOR]</link>
<link>plugin://plugin.video.elementum/play?uri=magnet:?xt=urn:btih:26e7445df0df53e6a7a03f0d4ed414582655507d$nome=[COLOR yellow]Série - A Agência 1ª Temp. Ep.06 (2025)[/COLOR]</link>
<link>plugin://plugin.video.elementum/play?uri=magnet:?xt=urn:btih:7be3a2ab9584d82294cccf55d6655648b3c9ea98$nome=[COLOR yellow]Série - A Agência 1ª Temp. Ep.07 (2025)[/COLOR]</link>
<thumbnail>https://image.tmdb.org/t/p/original/mRgfl4J0tVt3twmQ3C2zs8N5rG9.jpg</thumbnail>
<genre>Policial, Drama, Suspense</genre>
<fanart>https://image.tmdb.org/t/p/original/dD2X3iqtF4Dz3FpnYNSWud3LOrj.jpg</fanart>
<info>Martian é um agente da CIA forçado a abandonar sua vida secreta e voltar para Londres. Lá, ele precisa lidar com um antigo amor que reaparece, reacendendo sentimentos e dilemas.</info>
</item>


</items>
